aebo_pi/__init__.py
aebo_pi-0.8.dist-info/METADATA
aebo_pi-0.8.dist-info/WHEEL
aebo_pi-0.8.dist-info/top_level.txt
aebo_pi-0.8.dist-info/RECORD
